.gitignore
.gitmodules
.travis.yml
.woodpecker.yaml
AUTHORS
CHANGES.rst
LICENSE
MANIFEST.in
README.rst
appveyor.yml
setup.cfg
setup.py
.circleci/config.yml
conda-recipe/meta.yaml
examples/van_der_pol.ipynb
examples/van_der_pol.png
examples/van_der_pol.py
examples/tests/test_examples.py
external/anyode/LICENSE
external/anyode/cython_def/anyode.pxd
external/anyode/cython_def/anyode_numpy.pxd
external/anyode/include/anyode/anyode.hpp
external/anyode/include/anyode/anyode_blas_lapack.hpp
external/anyode/include/anyode/anyode_blasless.hpp
external/anyode/include/anyode/anyode_buffer.hpp
external/anyode/include/anyode/anyode_decomposition.hpp
external/anyode/include/anyode/anyode_decomposition_lapack.hpp
external/anyode/include/anyode/anyode_iterative.hpp
external/anyode/include/anyode/anyode_matrix.hpp
external/anyode/include/anyode/anyode_numpy.hpp
external/anyode/include/anyode/anyode_numpy_types.hpp
external/anyode/include/anyode/anyode_parallel.hpp
external/anyode/include/anyode/anyode_util.hpp
pyodeint/__init__.py
pyodeint/_odeint.cpp
pyodeint/_odeint.pyx
pyodeint/_release.py
pyodeint/_util.py
pyodeint.egg-info/PKG-INFO
pyodeint.egg-info/SOURCES.txt
pyodeint.egg-info/dependency_links.txt
pyodeint.egg-info/requires.txt
pyodeint.egg-info/top_level.txt
pyodeint/include/odeint_anyode.hpp
pyodeint/include/odeint_anyode.pxd
pyodeint/include/odeint_anyode_nogil.pxd
pyodeint/include/odeint_anyode_parallel.hpp
pyodeint/include/odeint_anyode_parallel.pxd
pyodeint/include/boost/numeric/odeint/stepper/rosenbrock4_controller.hpp
pyodeint/tests/__init__.py
pyodeint/tests/test_odeint_numpy.py
scripts/build_conda_recipe.sh
scripts/check_clean_repo_on_master.sh
scripts/ci.sh
scripts/coverage_badge.py
scripts/dir_to_branch.sh
scripts/generate_docs.sh
scripts/github_upload.sh
scripts/post_release.sh
scripts/prepare_deploy.sh
scripts/rasterize.js
scripts/release.sh
scripts/render_index.sh
scripts/render_notebooks.sh
scripts/run_tests.sh
scripts/update-gh-pages.sh
tests/Makefile
tests/_odeint_anyode.pyx
tests/_odeint_anyode.pyxbld
tests/_test_odeint_anyode.py
tests/cetsa_case.hpp
tests/doctest.h.bz2
tests/doctest.h.url
