Metadata-Version: 2.4
Name: pyodeint
Version: 0.10.8
Summary: Python binding for odeint from boost.
Home-page: https://github.com/bjodah/pyodeint
Author: Björn Dahlgren
Author-email: bjodah@DELETEMEgmail.com
License: BSD
Classifier: Development Status :: 4 - Beta
Classifier: License :: OSI Approved :: BSD License
Classifier: Operating System :: OS Independent
Classifier: Topic :: Scientific/Engineering
Classifier: Topic :: Scientific/Engineering :: Mathematics
License-File: LICENSE
License-File: AUTHORS
Requires-Dist: numpy
Requires-Dist: cython
Provides-Extra: docs
Requires-Dist: Sphinx; extra == "docs"
Requires-Dist: sphinx_rtd_theme; extra == "docs"
Dynamic: author
Dynamic: author-email
Dynamic: classifier
Dynamic: description
Dynamic: home-page
Dynamic: license
Dynamic: license-file
Dynamic: provides-extra
Dynamic: requires-dist
Dynamic: summary
